blender_addon_tester/__init__.py
blender_addon_tester/addon_helper.py
blender_addon_tester/blender_load_pytest.py
blender_addon_tester/blender_requirements.txt
blender_addon_tester/get_blender.py
blender_addon_tester/requirements.txt
blender_addon_tester/run_blender.py
blender_addon_tester-0.10.2.dist-info/LICENSE
blender_addon_tester-0.10.2.dist-info/METADATA
blender_addon_tester-0.10.2.dist-info/WHEEL
blender_addon_tester-0.10.2.dist-info/top_level.txt
blender_addon_tester-0.10.2.dist-info/RECORD
