Metadata-Version: 2.1
Name: blender-addon-tester
Version: 0.10.2
Summary: Add-On Tester for Blender using Pytest
Home-page: https://github.com/nangtani/blender-addon-tester
Author: Dave Keeshan
Author-email: dave.keeshan@daxzio.com
License: MIT
Platform: UNKNOWN
Classifier: Development Status :: 2 - Pre-Alpha
Classifier: Topic :: Artistic Software
Classifier: License :: OSI Approved :: MIT License
Requires-Python: >=3.7
License-File: LICENSE
Requires-Dist: bs4
Requires-Dist: dmglib
Requires-Dist: flake8
Requires-Dist: requests
